mail_office/__init__.py
mail_office/admin.py
mail_office/apps.py
mail_office/mail_office.py
mail_office/management/__init__.py
mail_office/management/commands/__init__.py
mail_office/management/commands/start_mailing.py
mail_office/migrations/0001_initial.py
mail_office/migrations/0002_auto_20210420_1701.py
mail_office/migrations/0003_auto_20210420_1716.py
mail_office/migrations/__init__.py
mail_office/models.py
mail_office/postman.py
mail_office/queue_.py
mail_office/settings.py
django_mail_office-0.9.9.dist-info/WHEEL
django_mail_office-0.9.9.dist-info/METADATA
django_mail_office-0.9.9.dist-info/RECORD
